AryaLogger/__init__.py
AryaLogger/AryaLogger.py
AryaLogger/convert_apic_dn_to_cobra.py
AryaLogger/version.py
AryaLogger-1.1.5.data/scripts/AryaLogger.py
AryaLogger-1.1.5.dist-info/DESCRIPTION.rst
AryaLogger-1.1.5.dist-info/entry_points.txt
AryaLogger-1.1.5.dist-info/METADATA
AryaLogger-1.1.5.dist-info/metadata.json
AryaLogger-1.1.5.dist-info/RECORD
AryaLogger-1.1.5.dist-info/top_level.txt
AryaLogger-1.1.5.dist-info/WHEEL
