Metadata-Version: 2.0
Name: AryaLogger
Version: 1.1.5
Summary: Use the SimpleAciUiLogServer and arya to convert UI REST API calls to ACI Python SDK code.
Home-page: https://github.com/datacenter/AryaLogger
Author: Mike Timm
Author-email: mtimm@cisco.com
License: AryaLogger
Requires-Dist: SimpleAciUiLogServer
Requires-Dist: acicobra
Requires-Dist: arya
